setup.py
distributions_binomial/Binomialdistribution.py
distributions_binomial/Gaussiandistribution.py
distributions_binomial/Generaldistribution.py
distributions_binomial/__init__.py
distributions_binomial.egg-info/PKG-INFO
distributions_binomial.egg-info/SOURCES.txt
distributions_binomial.egg-info/dependency_links.txt
distributions_binomial.egg-info/not-zip-safe
distributions_binomial.egg-info/top_level.txt