Metadata-Version: 1.0
Name: distributions-binomial
Version: 0.1
Summary: Gaussian distributions
Home-page: UNKNOWN
Author: Patrick Ruejoma
Author-email: pruejoma@gmail.com
License: UNKNOWN
Platform: UNKNOWN
